pyptables/__init__.py
pyptables/__main__.py
pyptables/base.py
pyptables/chains.py
pyptables/tables.py
pyptables/rules/__init__.py
pyptables/rules/arguments.py
pyptables/rules/base.py
pyptables/rules/marks.py
pyptables/rules/matches.py
pyptables/rules/forwarding/__init__.py
pyptables/rules/forwarding/base.py
pyptables/rules/forwarding/channels.py
pyptables/rules/forwarding/hosts.py
pyptables/rules/forwarding/ipsets.py
pyptables/rules/forwarding/locations.py
pyptables/rules/forwarding/zones.py
pyptables/rules/input/__init__.py
pyptables/rules/input/base.py
pyptables/test/__init__.py
PyPTables-1.0.7.dist-info/LICENSE.txt
PyPTables-1.0.7.dist-info/METADATA
PyPTables-1.0.7.dist-info/WHEEL
PyPTables-1.0.7.dist-info/top_level.txt
PyPTables-1.0.7.dist-info/RECORD
