Metadata-Version: 2.1
Name: PyPTables
Version: 1.0.7
Summary: Python package for generating Linux iptables configurations.
Home-page: https://github.com/daggaz/python-pyptables
Author: Jamie Cockburn
Author-email: jamie_cockburn@hotmail.co.uk
License: LICENSE.txt
Keywords: iptables,firewall
Platform: UNKNOWN
Classifier: Development Status :: 5 - Production/Stable
Classifier: Programming Language :: Python :: 2.7
Classifier: Programming Language :: Python :: 3
Classifier: Topic :: System :: Networking :: Firewalls
Classifier: License :: OSI Approved :: GNU General Public License v2 (GPLv2)
Classifier: Operating System :: POSIX :: Linux
License-File: LICENSE.txt
